clt/__init__.py
clt/activation_generation/__init__.py
clt/activation_generation/generator.py
clt/activations/__init__.py
clt/activations/registry.py
clt/config/__init__.py
clt/config/clt_config.py
clt/config/data_config.py
clt/models/__init__.py
clt/models/activations.py
clt/models/activations_distributed.py
clt/models/activations_local_global.py
clt/models/activations_optimized.py
clt/models/base.py
clt/models/clt.py
clt/models/decoder.py
clt/models/encoder.py
clt/models/parallel.py
clt/models/theta.py
clt/nnsight/__init__.py
clt/nnsight/extractor.py
clt/parallel/ops.py
clt/training/__init__.py
clt/training/checkpointing.py
clt/training/diagnostics.py
clt/training/distributed_utils.py
clt/training/evaluator.py
clt/training/losses.py
clt/training/metric_utils.py
clt/training/profiler.py
clt/training/trainer.py
clt/training/utils.py
clt/training/wandb_logger.py
clt/training/data/__init__.py
clt/training/data/activation_store_factory.py
clt/training/data/base_store.py
clt/training/data/local_activation_store.py
clt/training/data/manifest_activation_store.py
clt/training/data/remote_activation_store.py
clt/utils/__init__.py
clt/utils/io.py
clt_server/main.py
clt_server/api/__init__.py
clt_server/api/health.py
clt_server/core/__init__.py
clt_server/core/config.py
clt_server/core/storage.py
clt_server/tests/__init__.py
clt_server/tests/api/test_health.py
clt_server/tests/core/__init__.py
clt_server/tests/core/test_config.py
clt_server/tests/core/test_storage_manager.py
decode_clt-0.0.1.dist-info/licenses/LICENSE
decode_clt-0.0.1.dist-info/METADATA
decode_clt-0.0.1.dist-info/WHEEL
decode_clt-0.0.1.dist-info/top_level.txt
decode_clt-0.0.1.dist-info/RECORD
