Metadata-Version: 2.4
Name: decode-clt
Version: 0.0.1
Summary: Cross-Layer Transcoder Library
Classifier: Programming Language :: Python :: 3
Classifier: License :: OSI Approved :: MIT License
Classifier: Operating System :: OS Independent
Requires-Python: >=3.8
License-File: LICENSE
Requires-Dist: torch>=2.0.0
Requires-Dist: torchvision>=0.15.1
Requires-Dist: torchaudio>=2.0.1
Requires-Dist: nnsight>=0.1.0
Requires-Dist: transformers>=4.30.0
Requires-Dist: datasets>=2.0.0
Requires-Dist: wandb>=0.15.0
Requires-Dist: tqdm>=4.64.0
Requires-Dist: numpy>=1.24.0
Requires-Dist: zstandard
Requires-Dist: h5py
Requires-Dist: requests
Provides-Extra: dev
Requires-Dist: pytest; extra == "dev"
Requires-Dist: pytest-cov; extra == "dev"
Requires-Dist: black>=23.0.0; extra == "dev"
Requires-Dist: flake8>=6.0.0; extra == "dev"
Requires-Dist: mypy>=1.0.0; extra == "dev"
Dynamic: license-file
